__init__.py
aws_cron_expression_validator/__init__.py
aws_cron_expression_validator/validator.py
aws_cron_expression_validator-1.1.13.dist-info/LICENSE
aws_cron_expression_validator-1.1.13.dist-info/METADATA
aws_cron_expression_validator-1.1.13.dist-info/WHEEL
aws_cron_expression_validator-1.1.13.dist-info/top_level.txt
aws_cron_expression_validator-1.1.13.dist-info/RECORD
