Metadata-Version: 2.1
Name: aws-cron-expression-validator
Version: 1.1.13
Summary: ValidatesAWS EventBridge cron expressions, which are similar to, but not compatible with Unix style cron expressions
Author-email: Graham Coster <bitjugglers@gmail.com>
Project-URL: Homepage, https://github.com/grumBit/aws_cron_expression_validator.git
Project-URL: Bug Tracker, https://github.com/grumBit/aws_cron_expression_validator/issues
Project-URL: Source, https://github.com/grumBit/aws_cron_expression_validator
Project-URL: Security Policy, https://github.com/grumbit/aws_cron_expression_validator/blob/master/.github/SECURITY.md
Project-URL: Release Notes, https://github.com/grumBit/aws_cron_expression_validator/blob/master/RELEASENOTES.md
Classifier: Development Status :: 5 - Production/Stable
Classifier: Programming Language :: Python :: 3
Classifier: License :: OSI Approved :: MIT License
Classifier: Operating System :: OS Independent
Requires-Python: >=3.7
License-File: LICENSE
